odoo/addons/fieldservice_stock_account_analytic/README.rst
odoo/addons/fieldservice_stock_account_analytic/__init__.py
odoo/addons/fieldservice_stock_account_analytic/__manifest__.py
odoo/addons/fieldservice_stock_account_analytic/i18n/de.po
odoo/addons/fieldservice_stock_account_analytic/i18n/es.po
odoo/addons/fieldservice_stock_account_analytic/i18n/es_AR.po
odoo/addons/fieldservice_stock_account_analytic/i18n/es_CL.po
odoo/addons/fieldservice_stock_account_analytic/i18n/fieldservice_stock_account_analytic.pot
odoo/addons/fieldservice_stock_account_analytic/i18n/it.po
odoo/addons/fieldservice_stock_account_analytic/i18n/pt_BR.po
odoo/addons/fieldservice_stock_account_analytic/i18n/pt_PT.po
odoo/addons/fieldservice_stock_account_analytic/models/__init__.py
odoo/addons/fieldservice_stock_account_analytic/models/fsm_order.py
odoo/addons/fieldservice_stock_account_analytic/models/stock_request.py
odoo/addons/fieldservice_stock_account_analytic/readme/CONTRIBUTORS.rst
odoo/addons/fieldservice_stock_account_analytic/readme/DESCRIPTION.rst
odoo/addons/fieldservice_stock_account_analytic/readme/ROADMAP.rst
odoo/addons/fieldservice_stock_account_analytic/readme/USAGE.rst
odoo/addons/fieldservice_stock_account_analytic/static/description/icon.png
odoo/addons/fieldservice_stock_account_analytic/static/description/index.html
odoo/addons/fieldservice_stock_account_analytic/tests/__init__.py
odoo/addons/fieldservice_stock_account_analytic/tests/test_fsm_stock_account_analytic.py
odoo14_addon_fieldservice_stock_account_analytic-14.0.1.0.1.dev12.dist-info/METADATA
odoo14_addon_fieldservice_stock_account_analytic-14.0.1.0.1.dev12.dist-info/WHEEL
odoo14_addon_fieldservice_stock_account_analytic-14.0.1.0.1.dev12.dist-info/top_level.txt
odoo14_addon_fieldservice_stock_account_analytic-14.0.1.0.1.dev12.dist-info/RECORD
