Metadata-Version: 2.1
Name: odoo14-addon-fieldservice_stock_account_analytic
Version: 14.0.1.0.1.dev12
Summary: Track costs of delivered items with analytic accounting
Home-page: https://github.com/OCA/field-service
Author: Open Source Integrators, Odoo Community Association (OCA)
Author-email: support@odoo-community.org
License: AGPL-3
Classifier: Programming Language :: Python
Classifier: Framework :: Odoo
Classifier: Framework :: Odoo :: 14.0
Classifier: License :: OSI Approved :: GNU Affero General Public License v3
Classifier: Development Status :: 4 - Beta
Requires-Python: >=3.6
Requires-Dist: odoo14-addon-fieldservice-account-analytic
Requires-Dist: odoo14-addon-fieldservice-stock-account
Requires-Dist: odoo14-addon-stock-request-analytic
Requires-Dist: odoo <14.1dev,>=14.0a
